skdaccess
