Metadata-Version: 2.1
Name: scikit-dataaccess
Version: 1.9.17.post2
Summary: Scikit Data Access Package for accessing scientific data sets.
Home-page: https://github.com/MITHaystack/scikit-dataaccess
Author: MITHAGI
Author-email: skdaccess@mit.edu
License: UNKNOWN
Platform: UNKNOWN
Classifier: Topic :: Scientific/Engineering
Classifier: Intended Audience :: Science/Research
Classifier: License :: OSI Approved :: MIT License
Classifier: Programming Language :: Python :: 3 :: Only
Requires-Python: >=3.4
